{
  "status": {
    "code": "S",
    "description": ""
  },
  "result": [
    {
      "id": 1,
      "companyName": "Dreams Technologies",
      "contactPerson": "John Doe",
      "email": "john.doe@dreamspos.com",
      "phone": "+1 234 567 890",
      "address": "123 Dream St, Silicon Valley, CA",
      "city": "San Jose",
      "state": "CA",
      "zip": "95112",
      "country": "USA",
      "status": "Active"
    },
    {
      "id": 2,
      "companyName": "Tech Innovations",
      "contactPerson": "Jane Smith",
      "email": "jane.smith@techinnov.com",
      "phone": "+1 987 654 321",
      "address": "456 Innovation Blvd, New York, NY",
      "city": "New York",
      "state": "NY",
      "zip": "10001",
      "country": "USA",
      "status": "Inactive"
    },
    {
      "id": 3,
      "companyName": "Future Solutions",
      "contactPerson": "Michael Johnson",
      "email": "michael.j@futuresol.com",
      "phone": "+44 20 7946 0958",
      "address": "789 Future Rd, London",
      "city": "London",
      "state": "",
      "zip": "SW1A 1AA",
      "country": "UK",
      "status": "Active"
    },
    {
      "id": 4,
      "companyName": "NextGen Corp",
      "contactPerson": "Emily Davis",
      "email": "emily.d@nextgencorp.com",
      "phone": "+61 2 9374 4000",
      "address": "101 NextGen Ave, Sydney",
      "city": "Sydney",
      "state": "NSW",
      "zip": "2000",
      "country": "Australia",
      "status": "Active"
    },
    {
      "id": 5,
      "companyName": "Alpha Enterprises",
      "contactPerson": "Robert Brown",
      "email": "robert.b@alphaent.com",
      "phone": "+49 30 123456",
      "address": "202 Alpha St, Berlin",
      "city": "Berlin",
      "state": "",
      "zip": "10115",
      "country": "Germany",
      "status": "Inactive"
    },
    {
      "id": 6,
      "companyName": "Beta Technologies",
      "contactPerson": "Linda Wilson",
      "email": "linda.w@betatech.com",
      "phone": "+81 3 1234 5678",
      "address": "303 Beta Rd, Tokyo",
      "city": "Tokyo",
      "state": "",
      "zip": "100-0001",
      "country": "Japan",
      "status": "Active"
    },
    {
      "id": 7,
      "companyName": "Gamma Solutions",
      "contactPerson": "David Lee",
      "email": "david.l@gammasol.com",
      "phone": "+33 1 2345 6789",
      "address": "404 Gamma Blvd, Paris",
      "city": "Paris",
      "state": "",
      "zip": "75001",
      "country": "France",
      "status": "Active"
    },
    {
      "id": 8,
      "companyName": "Delta Dynamics",
      "contactPerson": "Susan Clark",
      "email": "susan.c@deltadyn.com",
      "phone": "+39 06 12345678",
      "address": "505 Delta St, Rome",
      "city": "Rome",
      "state": "",
      "zip": "00100",
      "country": "Italy",
      "status": "Inactive"
    },
    {
      "id": 9,
      "companyName": "Epsilon Enterprises",
      "contactPerson": "Mark Turner",
      "email": "mark.t@epsilonent.com",
      "phone": "+55 11 1234 5678",
      "address": "606 Epsilon Ave, Sao Paulo",
      "city": "Sao Paulo",
      "state": "",
      "zip": "01000-000",
      "country": "Brazil",
      "status": "Active"
    },
    {
      "id": 10,
      "companyName": "Zeta Innovations",
      "contactPerson": "Patricia Moore",
      "email": "patricia.m@zetainnov.com",
      "phone": "+27 11 123 4567",
      "address": "707 Zeta Rd, Johannesburg",
      "city": "Johannesburg",
      "state": "",
      "zip": "2000",
      "country": "South Africa",
      "status": "Active"
    }
  ]
}